fletbox/__init__.py
fletbox/fletbox.py
fletbox-0.3.0.dist-info/METADATA
fletbox-0.3.0.dist-info/WHEEL
fletbox-0.3.0.dist-info/licenses/LICENSE
fletbox-0.3.0.dist-info/RECORD
