Metadata-Version: 2.1
Name: fletbox
Version: 0.3.0
Summary: A box for flet, abusing contextmanagers and decorators
Project-URL: Homepage, https://github.com/Xynonners/fletbox
Project-URL: Bug Tracker, https://github.com/Xynonners/fletbox/issues
Author: Xynon
License-File: LICENSE
Classifier: Development Status :: 3 - Alpha
Classifier: License :: OSI Approved :: GNU Lesser General Public License v3 or later (LGPLv3+)
Classifier: Operating System :: OS Independent
Classifier: Programming Language :: Python :: 3
Requires-Python: >=3.7
Requires-Dist: flet
Requires-Dist: rich
Requires-Dist: simpleroute
